utils4mathpy/__init__.py
utils4mathpy/divisors.py
utils4mathpy/divisors_options.py
utils4mathpy/error_messages.py
utils4mathpy/factorize.py
utils4mathpy/is_prime.py
utils4mathpy/sieve.py
utils4mathpy-0.0.6.dist-info/LICENSE
utils4mathpy-0.0.6.dist-info/METADATA
utils4mathpy-0.0.6.dist-info/WHEEL
utils4mathpy-0.0.6.dist-info/top_level.txt
utils4mathpy-0.0.6.dist-info/RECORD
