Metadata-Version: 2.1
Name: utils4mathpy
Version: 0.0.6
Summary: Math tools package for python
Author: ManelRosPuig (Manel Ros Puig)
Author-email: <manel.rospuig@gmail.com>
Keywords: python,math,tools,numbers,prime numbers,utils4mathpy,divisors,factorize
License-File: LICENSE
